odoo/addons/pms_ocr_klippa/README.rst
odoo/addons/pms_ocr_klippa/__init__.py
odoo/addons/pms_ocr_klippa/__manifest__.py
odoo/addons/pms_ocr_klippa/data/pms_ocr_klippa_data.xml
odoo/addons/pms_ocr_klippa/models/__init__.py
odoo/addons/pms_ocr_klippa/models/klippa_log.py
odoo/addons/pms_ocr_klippa/models/pms_property.py
odoo/addons/pms_ocr_klippa/models/res_partner_id_category.py
odoo/addons/pms_ocr_klippa/readme/CONTRIBUTORS.rst
odoo/addons/pms_ocr_klippa/readme/DESCRIPTION.rst
odoo/addons/pms_ocr_klippa/readme/USAGE.rst
odoo/addons/pms_ocr_klippa/security/ir.model.access.csv
odoo/addons/pms_ocr_klippa/static/description/icon.png
odoo/addons/pms_ocr_klippa/static/description/index.html
odoo/addons/pms_ocr_klippa/views/klippa_log_views.xml
odoo/addons/pms_ocr_klippa/views/res_partner_id_category_views.xml
odoo14_addon_pms_ocr_klippa-14.0.1.0.2.dev17.dist-info/METADATA
odoo14_addon_pms_ocr_klippa-14.0.1.0.2.dev17.dist-info/WHEEL
odoo14_addon_pms_ocr_klippa-14.0.1.0.2.dev17.dist-info/top_level.txt
odoo14_addon_pms_ocr_klippa-14.0.1.0.2.dev17.dist-info/RECORD
